raptor_stats-0.0.5.dist-info/licenses/LICENSE
raptorstats/__init__.py
raptorstats/agqt.py
raptorstats/api.py
raptorstats/io.py
raptorstats/node.py
raptorstats/scanline.py
raptorstats/stats.py
raptorstats/zonal_stat_method.py
raptor_stats-0.0.5.dist-info/METADATA
raptor_stats-0.0.5.dist-info/WHEEL
raptor_stats-0.0.5.dist-info/top_level.txt
raptor_stats-0.0.5.dist-info/RECORD
