Metadata-Version: 2.4
Name: raptor-stats
Version: 0.0.5
Summary: Raptor Zonal Statistics
Author-email: Simon Pedro Gonzalez <simon.pedro.g@gmail.com>
Requires-Python: >=3.12
License-File: LICENSE
Requires-Dist: affine>=2.4.0
Requires-Dist: geopandas>=1.0.1
Requires-Dist: rasterio>=1.4.3
Requires-Dist: rtree>=1.4.0
Provides-Extra: dev
Requires-Dist: tqdm>=4.67.1; extra == "dev"
Requires-Dist: rasterstats>=0.20.0; extra == "dev"
Requires-Dist: xarray>=2025.1.1; extra == "dev"
Requires-Dist: line-profiler>=4.2.0; extra == "dev"
Requires-Dist: memory-profiler>=0.61.0; extra == "dev"
Requires-Dist: ruff>=0.11.2; extra == "dev"
Requires-Dist: seaborn>=0.13.2; extra == "dev"
Requires-Dist: pyqt6>=6.8.0; extra == "dev"
Requires-Dist: rasterstats>=0.20.0; extra == "dev"
Requires-Dist: psutil>=7.0.0; extra == "dev"
Requires-Dist: matplotlib>=3.7.1; extra == "dev"
Requires-Dist: pytest>=8.4.1; extra == "dev"
Requires-Dist: isort>=6.0.1; extra == "dev"
Requires-Dist: black>=25.1.0; extra == "dev"
Requires-Dist: docformatter>=1.7.7; extra == "dev"
Requires-Dist: pydocstyle>=6.3.0; extra == "dev"
Requires-Dist: m2r>=0.3.1; extra == "dev"
Requires-Dist: sphinx>=8.2.3; extra == "dev"
Requires-Dist: sphinx_rtd_theme>=3.0.2; extra == "dev"
Requires-Dist: build>=1.3.0; extra == "dev"
Dynamic: license-file
